streamjam/__init__.py
StreamJam-0.0.1.dist-info/LICENSE
StreamJam-0.0.1.dist-info/METADATA
StreamJam-0.0.1.dist-info/WHEEL
StreamJam-0.0.1.dist-info/top_level.txt
StreamJam-0.0.1.dist-info/RECORD
