Metadata-Version: 2.1
Name: StreamJam
Version: 0.0.1
Summary: Unifying frontend and backend into one Pythonic experience for sleek, interactive web apps.
Home-page: https://github.com/creativesands/streamjam
Author: Sandeep S Kumar
Author-email: sanygeek@gmail.com
Classifier: Programming Language :: Python :: 3
Classifier: License :: OSI Approved :: MIT License
Classifier: Operating System :: OS Independent
License-File: LICENSE
